LICENSE
README.md
setup.py
calibration/__init__.py
calibration/calibrators.py
calibration/util_test.py
calibration/utils.py
uncertainty_calibration.egg-info/PKG-INFO
uncertainty_calibration.egg-info/SOURCES.txt
uncertainty_calibration.egg-info/dependency_links.txt
uncertainty_calibration.egg-info/requires.txt
uncertainty_calibration.egg-info/top_level.txt