Metadata-Version: 2.1
Name: uncertainty-calibration
Version: 0.1.3
Summary: Utilities to calibrate model uncertainties and measure calibration.
Home-page: https://github.com/AnanyaKumar/verified_calibration
Author: Ananya Kumar
Author-email: skywalker94@gmail.com
License: UNKNOWN
Platform: UNKNOWN
Classifier: Programming Language :: Python :: 3
Classifier: License :: OSI Approved :: MIT License
Classifier: Operating System :: OS Independent
Requires-Python: >=3.6
License-File: LICENSE
